skr.py
skr-0.1.0.dist-info/METADATA
skr-0.1.0.dist-info/RECORD
skr-0.1.0.dist-info/WHEEL
skr-0.1.0.dist-info/entry_points.txt
skr-0.1.0.dist-info/top_level.txt
