Metadata-Version: 2.1
Name: skr
Version: 0.1.0
Summary: SkrSkr in Python.
Home-page: https://github.com/chenjiandongx/skrskr
Author: chenjiandongx
Author-email: chenjiandongx@qq.com
License: MIT
Platform: UNKNOWN
Requires-Dist: pywin32
